{
    "uuid": "ead999a3-5e5e-5ed4-ad75-74f9d09e9e3c",
    "title": "Click: Controllable Text Generation with Sequence Likelihood Contrastive Learning",
    "conference_full": "Annual Meeting of the Association for Computational Linguistics",
    "conference": "ACL",
    "year": 2023,
    "volume": "Findings of the Association for Computational Linguistics: ACL 2023",
    "bibtex": "@inproceedings{zheng-etal-2023-click,\n    title = \"Click: Controllable Text Generation with Sequence Likelihood Contrastive Learning\",\n    author = \"Zheng, Chujie  and\n      Ke, Pei  and\n      Zhang, Zheng  and\n      Huang, Minlie\",\n    editor = \"Rogers, Anna  and\n      Boyd-Graber, Jordan  and\n      Okazaki, Naoaki\",\n    booktitle = \"Findings of the Association for Computational Linguistics: ACL 2023\",\n    month = jul,\n    year = \"2023\",\n    address = \"Toronto, Canada\",\n    publisher = \"Association for Computational Linguistics\",\n    url = \"https://aclanthology.org/2023.findings-acl.65\",\n    doi = \"10.18653/v1/2023.findings-acl.65\",\n    pages = \"1022--1040\",\n    abstract = \"It has always been an important yet challenging problem to control language models to avoid generating texts with undesirable attributes, such as toxic language and unnatural repetition. We introduce Leo for controllable text generation, which needs no modification to the model architecture and facilitates out-of-the-box use of trained models. It employs a contrastive loss on sequence likelihood, which fundamentally decreases the generation probability of negative samples (i.e., generations with undesirable attributes). It also adopts a novel likelihood ranking-based strategy to construct contrastive samples from model generations. On the tasks of language detoxification, sentiment steering, and repetition reduction, we show that Leo outperforms strong baselines of controllable text generation and demonstrate the superiority of Leo{'}s sample construction strategy.\",\n}\n",
    "authors": [
        "Chujie Zheng",
        "Pei Ke",
        "Zheng Zhang",
        "Minlie Huang"
    ],
    "pdf_url": "https://aclanthology.org/2023.findings-acl.65.pdf",
    "pdf_path": "data/dataset/airqa/papers/acl2023/ead999a3-5e5e-5ed4-ad75-74f9d09e9e3c.pdf",
    "abstract": "It has always been an important yet challenging problem to control language models to avoid generating texts with undesirable attributes, such as toxic language and unnatural repetition. We introduce Leo for controllable text generation, which needs no modification to the model architecture and facilitates out-of-the-box use of trained models. It employs a contrastive loss on sequence likelihood, which fundamentally decreases the generation probability of negative samples (i.e., generations with undesirable attributes). It also adopts a novel likelihood ranking-based strategy to construct contrastive samples from model generations. On the tasks of language detoxification, sentiment steering, and repetition reduction, we show that Leo outperforms strong baselines of controllable text generation and demonstrate the superiority of Leo’s sample construction strategy.",
    "num_pages": 19
}