{
    "uuid": "05548a18-0a57-54e2-a7d6-58a5a8cdca72",
    "question": "Is there any paper that performs adversarial training on frame level for audio-visual representation learning?",
    "answer_format": "Your answer should be the title of the paper WITHOUT ANY EXPLANATION.",
    "tags": [
        "retrieval",
        "text",
        "subjective"
    ],
    "anchor_pdf": [],
    "reference_pdf": [],
    "conference": [
        "acl2023"
    ],
    "reasoning_steps": [],
    "evaluator": {
        "eval_func": "eval_paper_relevance_with_reference_answer",
        "eval_kwargs": {
            "question": "Is there any paper that performs adversarial training on frame level for audio-visual representation learning?",
            "reference_answer": "MIR-GAN: Refining Frame-Level Modality-Invariant Representations with Adversarial Network for Audio-Visual Speech Recognition"
        }
    },
    "state": {},
    "annotator": "litsearch_manual"
}