{
    "uuid": "b5307d05-348e-50df-8932-95ccf83020f0",
    "question": "Which paper investigates the influence of the diversity of source tasks on the performance of target tasks in prompt tuning using CrossFit?",
    "answer_format": "Your answer should be the title of the paper WITHOUT ANY EXPLANATION.",
    "tags": [
        "retrieval",
        "text",
        "subjective"
    ],
    "anchor_pdf": [],
    "reference_pdf": [],
    "conference": [
        "acl2023"
    ],
    "reasoning_steps": [],
    "evaluator": {
        "eval_func": "eval_paper_relevance_with_reference_answer",
        "eval_kwargs": {
            "question": "Which paper investigates the influence of the diversity of source tasks on the performance of target tasks in prompt tuning using CrossFit?",
            "reference_answer": "Learning to Initialize: Can Meta Learning Improve Cross-task Generalization in Prompt Tuning?"
        }
    },
    "state": {},
    "annotator": "litsearch_manual"
}