{
    "uuid": "e8654b21-dff6-5447-90f4-afb0974ce94d",
    "question": "Which backdoor paper first used the CLIP to suppress benign features and enhance poisoning features to design triggers?",
    "answer_format": "Your answer should be the title of the paper WITHOUT ANY EXPLANATION.",
    "tags": [
        "retrieval",
        "text",
        "subjective"
    ],
    "anchor_pdf": [],
    "reference_pdf": [],
    "conference": [
        "iclr2024"
    ],
    "reasoning_steps": [],
    "evaluator": {
        "eval_func": "eval_paper_relevance_with_reference_answer",
        "eval_kwargs": {
            "question": "Which backdoor paper first used the CLIP to suppress benign features and enhance poisoning features to design triggers?",
            "reference_answer": "Efficient Backdoor Attacks for Deep Neural Networks in Real-world Scenarios"
        }
    },
    "state": {},
    "annotator": "litsearch_manual"
}